pyoshub/__init__.py
pyoshub/pyoshub.py
pyoshub/test/__init__.py
pyoshub/test/test___init__.py
pyoshub/test/test__flatten_facilities_json.py
pyoshub/test/test_get_contributor_embed_configs.py
pyoshub/test/test_get_contributor_lists.py
pyoshub/test/test_get_contributor_types.py
pyoshub/test/test_get_contributors.py
pyoshub/test/test_get_countries.py
pyoshub/test/test_get_countries_active_count.py
pyoshub/test/test_get_facilities.py
pyoshub/test/test_get_facilities_count.py
pyoshub/test/test_get_facility.py
pyoshub/test/test_get_facility_processing_types.py
pyoshub/test/test_get_parent_companies.py
pyoshub/test/test_get_product_types.py
pyoshub/test/test_get_sectors.py
pyoshub/test/test_get_workers_ranges.py
pyoshub/test/test_post_facilities.py
pyoshub/test/test_post_facilities_bulk.py
pyoshub/test/cassettes/Test___init__.test_credentials_via_url.yaml
pyoshub/test/cassettes/Test___init__.test_dotenv.yaml
pyoshub/test/cassettes/Test___init__.test_dotenv_with_path.yaml
pyoshub/test/cassettes/Test___init__.test_invalid_protocol.yaml
pyoshub/test/cassettes/Test___init__.test_invalid_url.yaml
pyoshub/test/cassettes/Test___init__.test_valid_url.yaml
pyoshub/test/cassettes/Test___init__.test_valid_url_invalid_token.yaml
pyoshub/test/cassettes/Test___init__.test_valid_url_invalid_token_test_token.yaml
pyoshub/test/cassettes/Test___init__.test_valid_url_no_token_test_token.yaml
pyoshub/test/cassettes/Test___init__.test_valid_url_valid_token_test_token.yaml
pyoshub/test/cassettes/Test__flatten_facilities_json.test__flatten_facilities_json.yaml
pyoshub/test/cassettes/Test_get_contributor_embed_configs.test_get_contributor_embed_configs_invalid_id.yaml
pyoshub/test/cassettes/Test_get_contributor_embed_configs.test_get_contributor_embed_configs_valid_id.yaml
pyoshub/test/cassettes/Test_get_contributor_lists.test_get_contributor_lists_invalid.yaml
pyoshub/test/cassettes/Test_get_contributor_lists.test_get_contributor_lists_valid.yaml
pyoshub-0.5.1.dist-info/WHEEL
pyoshub-0.5.1.dist-info/METADATA
pyoshub-0.5.1.dist-info/RECORD
