Metadata-Version: 2.1
Name: pyoshub
Version: 0.5.1
Summary: pyoshub is a Package for accessing the https://opensupplyhub.org API using python.
Author-email: "Klaus G. Paul" <20340525+KlausGPaul@users.noreply.github.com>
Requires-Python: >=3.5
Classifier: Programming Language :: Python :: 3
Classifier: License :: OSI Approved :: MIT License
Classifier: Operating System :: OS Independent
Project-URL: Bug Tracker, https://github.com/opensupplyhub/pyoshub/issues
Project-URL: Documentation, https://pyoshub.readthedocs.io
Project-URL: Github, https://github.com/opensupplyhub/pyoshub
Project-URL: Homepage, https://opensupplyhub.org
Project-URL: OpenAPI, https://opensupplyhub.org/api/docs
